bfact/__init__.py
bfact/cli.py
bfact/metrics.py
bfact/models/__init__.py
bfact/models/base_funcs.py
bfact/models/double_IP.py
bfact/models/feature_prune.py
bfact/models/generate_candidate_factors.py
bfact/models/iterate_main.py
bfact/models/reassign_features.py
bfact/models/restricted_master_problem.py
bfact/run_bfact.py
bfact_core-0.1.2.dist-info/LICENSE
bfact_core-0.1.2.dist-info/METADATA
bfact_core-0.1.2.dist-info/WHEEL
bfact_core-0.1.2.dist-info/entry_points.txt
bfact_core-0.1.2.dist-info/RECORD
